setup.py
src/maidenhair_jasco_parser/__init__.py
src/maidenhair_jasco_parser.egg-info/PKG-INFO
src/maidenhair_jasco_parser.egg-info/SOURCES.txt
src/maidenhair_jasco_parser.egg-info/dependency_links.txt
src/maidenhair_jasco_parser.egg-info/entry_points.txt
src/maidenhair_jasco_parser.egg-info/requires.txt
src/maidenhair_jasco_parser.egg-info/top_level.txt
src/maidenhair_jasco_parser.egg-info/zip-safe