Metadata-Version: 1.1
Name: maidenhair-jasco-parser
Version: 0.1.0
Summary: maidenhair parser plugin for reading JASCO txt file
Home-page: UNKNOWN
Author: Alisue
Author-email: lambdalisue@hashnote.net
License: MIT
Keywords: maidenhair,JASCO,parser
Platform: UNKNOWN
Classifier: Intended Audience :: Developers
Classifier: License :: OSI Approved :: MIT License
Classifier: Programming Language :: Python
